fabric_mcp/__about__.py
fabric_mcp/__init__.py
fabric_mcp/api_client.py
fabric_mcp/cli.py
fabric_mcp/config.py
fabric_mcp/constants.py
fabric_mcp/core.py
fabric_mcp/fabric_tools.py
fabric_mcp/models.py
fabric_mcp/server_stdio.py
fabric_mcp/sse_parser.py
fabric_mcp/utils.py
fabric_mcp/validation.py
fabric_mcp-1.0.3.dist-info/METADATA
fabric_mcp-1.0.3.dist-info/WHEEL
fabric_mcp-1.0.3.dist-info/entry_points.txt
fabric_mcp-1.0.3.dist-info/licenses/LICENSE
fabric_mcp-1.0.3.dist-info/RECORD
