Metadata-Version: 2.4
Name: fabric-mcp
Version: 1.0.3
Summary: MCP Server for Fabric AI Framework
Project-URL: Homepage, https://github.com/ksylvan/fabric-mcp
Project-URL: Releases, https://github.com/ksylvan/fabric-mcp/releases
Project-URL: Bug Tracker, https://github.com/ksylvan/fabric-mcp/issues
Project-URL: Documentation, https://github.com/ksylvan/fabric-mcp#readme
Author-email: Kayvan Sylvan <kayvan@sylvan.com>
License: MIT
License-File: LICENSE
Keywords: ai,fabric,framework,mcp,server
Classifier: License :: OSI Approved :: MIT License
Classifier: Operating System :: OS Independent
Classifier: Programming Language :: Python :: 3
Requires-Python: >=3.11
Requires-Dist: click>=8.2.1
Requires-Dist: fastmcp>=2.8.1
Requires-Dist: httpx-retries>=0.4.0
Requires-Dist: httpx-sse>=0.4.0
Requires-Dist: httpx>=0.28.1
Requires-Dist: modelcontextprotocol>=0.1.0
Requires-Dist: python-dotenv>=1.1.0
Requires-Dist: rich>=14.0.0
